layer_loader/__init__.py
layer_loader/__main__.py
layer_loader/expansion.py
layer_loader/flatten.py
layer_loader/loader.py
layer_loader/py.typed
layer_loader/types.py
layer_loader-0.0.1.dist-info/LICENSE
layer_loader-0.0.1.dist-info/METADATA
layer_loader-0.0.1.dist-info/WHEEL
layer_loader-0.0.1.dist-info/top_level.txt
layer_loader-0.0.1.dist-info/zip-safe
layer_loader-0.0.1.dist-info/RECORD
