Metadata-Version: 2.1
Name: layer-loader
Version: 0.0.1
Summary: Easy composition of configuration files
Home-page: https://github.com/PeterJCLaw/layer-loader
Author: Peter Law
Author-email: PeterJCLaw@gmail.com
License: MIT
Project-URL: Issue tracker, https://github.com/PeterJCLaw/layer-loader/issues
Project-URL: Documentation, https://github.com/PeterJCLaw/layer-loader/blob/master/READNE.md
Project-URL: Code, https://github.com/PeterJCLaw/layer-loader
Platform: UNKNOWN
Classifier: Intended Audience :: Developers
Classifier: License :: OSI Approved :: MIT License
Classifier: Operating System :: OS Independent
Classifier: Programming Language :: Python :: 3
Classifier: Programming Language :: Python :: 3.5
Classifier: Programming Language :: Python :: 3.6
Classifier: Programming Language :: Python :: 3.7
Classifier: Programming Language :: Python :: 3.8
Classifier: Programming Language :: Python :: 3 :: Only
Classifier: Topic :: Software Development :: Libraries :: Python Modules
Classifier: Topic :: Utilities
Classifier: Typing :: Typed
